ecg_noise_detector/__init__.py
ecg_noise_detector/noiseDetector.py
ecg_noise_detector/data/clean_ecg.csv
ecg_noise_detector/data/model_20_05_21.joblib
ecg_noise_detector/data/noisy_ecg.csv
ecg_noise_detector-0.0.3.dist-info/LICENSE
ecg_noise_detector-0.0.3.dist-info/METADATA
ecg_noise_detector-0.0.3.dist-info/WHEEL
ecg_noise_detector-0.0.3.dist-info/top_level.txt
ecg_noise_detector-0.0.3.dist-info/RECORD
