Metadata-Version: 2.1
Name: ecg-noise-detector
Version: 0.0.3
Summary: Detect noise in ECGs
Home-page: https://github.com/Yoav11/ecg-noise-detector
Author: Yoav Nir
Author-email: 11yoav.nir@gmail.com
Project-URL: Bug Tracker, https://github.com/Yoav11/ecg-noise-detector/issues
Classifier: Programming Language :: Python :: 3
Classifier: License :: OSI Approved :: GNU General Public License v3 (GPLv3)
Classifier: Operating System :: OS Independent
Requires-Python: >=3.6
License-File: LICENSE
Requires-Dist: matplotlib
Requires-Dist: numpy
Requires-Dist: scipy
Requires-Dist: joblib
Requires-Dist: pandas
Requires-Dist: py-ecg-detectors
Requires-Dist: scikit-learn (==1.0.1)
